mimemapper/__init__.py
mimemapper/ext_to_mime.json
mimemapper/lib.py
mimemapper/mime_to_ext.json
mimemapper-0.4.0.dist-info/licenses/LICENSE
mimemapper-0.4.0.dist-info/METADATA
mimemapper-0.4.0.dist-info/WHEEL
mimemapper-0.4.0.dist-info/top_level.txt
mimemapper-0.4.0.dist-info/RECORD
