Metadata-Version: 2.4
Name: mimemapper
Version: 0.4.0
Summary: Convert between MIME types and extensions - straight from the IANA registry
Author-email: Safwan Samsudeen <safwansamsudeen.c@gmail.com>
License: MIT License
Project-URL: Homepage, https://github.com/safwansamsudeen/mimemapper
Keywords: mime,file,extensions
Classifier: License :: OSI Approved :: MIT License
Classifier: Programming Language :: Python
Classifier: Programming Language :: Python :: 3
Requires-Python: >=3.9
License-File: LICENSE
Dynamic: license-file
